sandwine/__init__.py
sandwine/__main__.py
sandwine/_main.py
sandwine/_x11.py
sandwine-5.0.0.dist-info/licenses/COPYING
sandwine-5.0.0.dist-info/METADATA
sandwine-5.0.0.dist-info/WHEEL
sandwine-5.0.0.dist-info/entry_points.txt
sandwine-5.0.0.dist-info/top_level.txt
sandwine-5.0.0.dist-info/RECORD
