Metadata-Version: 2.4
Name: sandwine
Version: 5.0.0
Summary: Command-line tool to run Windows apps with Wine and bwrap/bubblewrap isolation
Author-email: Sebastian Pipping <sebastian@pipping.org>
License: GPLv3+
Project-URL: Homepage, https://github.com/hartwork/sandwine
Project-URL: Bug Tracker, https://github.com/hartwork/sandwine/issues
Keywords: Wine,sandbox,sandboxing,bubblewrap,bwrap
Classifier: Development Status :: 3 - Alpha
Classifier: License :: OSI Approved :: GNU General Public License v3 or later (GPLv3+)
Classifier: Intended Audience :: Developers
Classifier: Programming Language :: Python
Classifier: Programming Language :: Python :: 3
Classifier: Programming Language :: Python :: 3 :: Only
Classifier: Programming Language :: Python :: 3.10
Classifier: Programming Language :: Python :: 3.11
Classifier: Programming Language :: Python :: 3.12
Classifier: Programming Language :: Python :: 3.13
Classifier: Programming Language :: Python :: 3.14
Classifier: Intended Audience :: Developers
Classifier: Intended Audience :: End Users/Desktop
Classifier: Operating System :: Unix
Classifier: Topic :: Security
Classifier: Topic :: System :: Emulators
Requires-Python: >=3.10
License-File: COPYING
Requires-Dist: coloredlogs>=15.0.1
Dynamic: license-file
